MANIFEST.in
setup.py
configuration.py.egg-info/PKG-INFO
configuration.py.egg-info/SOURCES.txt
configuration.py.egg-info/dependency_links.txt
configuration.py.egg-info/not-zip-safe
configuration.py.egg-info/requires.txt
configuration.py.egg-info/top_level.txt
configuration_py/__init__.py
configuration_py/configuration_load.py
configuration_py/parser_lookup.py
configuration_py/parsers/__init__.py
configuration_py/parsers/__init__.pyc
configuration_py/parsers/base_parser.py
configuration_py/parsers/base_parser.pyc
configuration_py/parsers/json_parser.py
configuration_py/parsers/json_parser.pyc
configuration_py/parsers/string_template_processor.py
configuration_py/parsers/string_template_processor.pyc
configuration_py/parsers/yaml_parser.py
configuration_py/parsers/yaml_parser.pyc