Metadata-Version: 1.1
Name: configuration.py
Version: 0.8.3
Summary: Easy config management for python applications
Home-page: http://github.com/Ferroman/configuration.py
Author: Frankovskyi Bogdan
Author-email: bfrankovskyi@gmail.com
License: MIT
Platform: UNKNOWN
Classifier: Development Status :: 4 - Beta
Classifier: License :: OSI Approved :: MIT License
Classifier: Programming Language :: Python :: 2.7
Classifier: Topic :: Software Development :: Libraries :: Python Modules
